bugsplat/__init__.py
bugsplat/bugsplat.py
bugsplat-1.0.4.dist-info/METADATA
bugsplat-1.0.4.dist-info/WHEEL
bugsplat-1.0.4.dist-info/licenses/LICENSE
bugsplat-1.0.4.dist-info/RECORD
