Metadata-Version: 2.3
Name: bugsplat
Version: 1.0.4
Summary: A Python package for sending Unhandled Exceptions to BugSplat
Project-URL: Homepage, https://github.com/BugSplat-Git/bugsplat-py
Project-URL: Issues, https://github.com/BugSplat-Git/bugsplat-py/issues
Author-email: Bobby Galli <bobby@bugsplat.com>
License-File: LICENSE
Classifier: Development Status :: 4 - Beta
Classifier: Environment :: Console
Classifier: Environment :: Web Environment
Classifier: Intended Audience :: Developers
Classifier: License :: OSI Approved :: MIT License
Classifier: Operating System :: OS Independent
Classifier: Programming Language :: Python :: 3
Classifier: Programming Language :: Python :: 3 :: Only
Classifier: Programming Language :: Python :: 3.6
Classifier: Programming Language :: Python :: 3.7
Classifier: Programming Language :: Python :: 3.8
Classifier: Programming Language :: Python :: 3.9
Requires-Python: >=3.8
Requires-Dist: requests<=2.29.0
Provides-Extra: test
Requires-Dist: certifi==2022.6.15; extra == 'test'
Requires-Dist: charset-normalizer==2.0.12; extra == 'test'
Requires-Dist: idna==3.3; extra == 'test'
Requires-Dist: requests==2.29.0; extra == 'test'
Requires-Dist: urllib3==1.26.9; extra == 'test'
